MANIFEST.in
README.md
pyproject.toml
setup.py
ruleforge/__init__.py
ruleforge/builder.py
ruleforge/core.py
ruleforge/loader.py
ruleforge/validators.c
ruleforge/validators.pyx
ruleforge.egg-info/PKG-INFO
ruleforge.egg-info/SOURCES.txt
ruleforge.egg-info/dependency_links.txt
ruleforge.egg-info/requires.txt
ruleforge.egg-info/top_level.txt
tests/test_ruleforge.py