Metadata-Version: 2.4
Name: ruleforge
Version: 0.0.1
Summary: Very easy pop and play package to make pre-processing easier than before ;)
Author: Akash K Tesla
License: MIT
Requires-Python: >=3.8
Requires-Dist: pandas
